{
  "ultima_actualizacion": "2025-10-31T05:13:00.235051+00:00",
  "tasas": [
    {
      "entidad": "BANCO DE LA NACION ARGENTINA",
      "tna": 35.0
    },
    {
      "entidad": "BANCO SANTANDER ARGENTINA SOCIEDAD ANONIMA",
      "tna": 32.0
    },
    {
      "entidad": "BANCO DE GALICIA Y BUENOS AIRES S.A.",
      "tna": 31.0
    },
    {
      "entidad": "BANCO DE LA PROVINCIA DE BUENOS AIRES",
      "tna": 34.0
    },
    {
      "entidad": "BANCO BBVA ARGENTINA S.A.",
      "tna": 32.0
    }
  ]
}